pygcapi/__init__.py
pygcapi/core_v1.py
pygcapi/core_v2.py
pygcapi/utils.py
pygcapi-0.1.0.dist-info/LICENSE
pygcapi-0.1.0.dist-info/METADATA
pygcapi-0.1.0.dist-info/WHEEL
pygcapi-0.1.0.dist-info/RECORD
