Metadata-Version: 2.1
Name: pygcapi
Version: 0.1.0
Summary: Interface to the Gain Capital API V1 and V2, enabling users to perform various trading operations on Forex.com.
Home-page: https://github.com/athammad/pygcapi
License: MIT
Keywords: api,client,gc
Author: Ahmed T. Hammad
Author-email: ahmed.t.hammad@gmail.com
Requires-Python: >=3.11
Classifier: License :: OSI Approved :: MIT License
Classifier: Operating System :: OS Independent
Classifier: Programming Language :: Python :: 3
Classifier: Programming Language :: Python :: 3.11
Classifier: Programming Language :: Python :: 3.12
Classifier: Programming Language :: Python :: 3.13
Requires-Dist: pandas (>=1.3.0)
Requires-Dist: requests (>=2.0.0)
Project-URL: Repository, https://github.com/athammad/pygcapi
